html_modifier/__init__.py
html_modifier/html_modifier_service.py
html_modifier/server.py
html_modifier-0.1.2.dist-info/METADATA
html_modifier-0.1.2.dist-info/WHEEL
html_modifier-0.1.2.dist-info/entry_points.txt
html_modifier-0.1.2.dist-info/RECORD
